EzTDX/__init__.py
EzTDX/__main__.py
EzTDX-2021.11.16.dist-info/LICENSE.txt
EzTDX-2021.11.16.dist-info/METADATA
EzTDX-2021.11.16.dist-info/WHEEL
EzTDX-2021.11.16.dist-info/top_level.txt
EzTDX-2021.11.16.dist-info/RECORD
