Metadata-Version: 2.1
Name: EzTDX
Version: 2021.11.16
Summary: A Python interface to the TeamDynamix REST APIs
Home-page: https://github.com/cgarrett/eztdx
Author: Chris Garrett
Author-email: cmgarOK@gmail.com
License: GPLv3+
Project-URL: Bug Tracker, https://github.com/cgarrett/eztdx/issues
Platform: UNKNOWN
Classifier: Programming Language :: Python :: 3
Classifier: License :: OSI Approved :: GNU General Public License v3 (GPLv3)
Classifier: Operating System :: OS Independent
Classifier: Programming Language :: Python :: 3.4
Classifier: Programming Language :: Python :: 3.5
Classifier: Programming Language :: Python :: 3.6
Classifier: Programming Language :: Python :: 3.7
Requires-Python: >=3.6
License-File: LICENSE.txt
Requires-Dist: requests
